{"mapel":[{"id":63,"created_at":"2026-05-29T14:14:45.744+07:00","updated_at":"2026-05-29T14:14:45.744+07:00","instansi_id":"8f990e06-d717-4462-b9ec-df8a0388bf64","nama_mapel":"agama","kelompok":"","jurusan":"","slug":"agama-36a7a"},{"id":64,"created_at":"2026-05-29T14:14:45.745+07:00","updated_at":"2026-05-29T14:14:45.745+07:00","instansi_id":"8f990e06-d717-4462-b9ec-df8a0388bf64","nama_mapel":"mpp","kelompok":"","jurusan":"","slug":"mpp-2bf07"},{"id":65,"created_at":"2026-05-29T14:14:45.747+07:00","updated_at":"2026-05-29T14:14:45.747+07:00","instansi_id":"8f990e06-d717-4462-b9ec-df8a0388bf64","nama_mapel":"inggris","kelompok":"","jurusan":"","slug":"inggris-cb1df"}],"nilai":[],"siswa":[{"ID":0,"CreatedAt":"2026-05-29T14:14:45.71+07:00","UpdatedAt":"2026-05-29T14:14:45.71+07:00","DeletedAt":null,"id":"ece0a012-f03e-44a9-b3c3-1206a0dcec5d","instansi_id":"8f990e06-d717-4462-b9ec-df8a0388bf64","foto_siswa":"","nisn":"2027202810","nama_siswa":"udin","tempat_lahir":"Jakarta","tanggal_lahir":"01-01-07","jenis_kelamin":"","kelas":"L","jurusan":"FALSE","tahun_lulus":"2026","nama_wali":"","status_lulus":false,"nilai":null}]}